openrlhf-0.9.1.post1.data/purelib/openrlhf/__init__.py
openrlhf-0.9.1.post1.data/purelib/openrlhf/cli/__init__.py
openrlhf-0.9.1.post1.data/purelib/openrlhf/cli/batch_inference.py
openrlhf-0.9.1.post1.data/purelib/openrlhf/cli/interactive_chat.py
openrlhf-0.9.1.post1.data/purelib/openrlhf/cli/lora_combiner.py
openrlhf-0.9.1.post1.data/purelib/openrlhf/cli/serve_rm.py
openrlhf-0.9.1.post1.data/purelib/openrlhf/cli/train_dpo.py
openrlhf-0.9.1.post1.data/purelib/openrlhf/cli/train_kd.py
openrlhf-0.9.1.post1.data/purelib/openrlhf/cli/train_kto.py
openrlhf-0.9.1.post1.data/purelib/openrlhf/cli/train_ppo_ray.py
openrlhf-0.9.1.post1.data/purelib/openrlhf/cli/train_prm.py
openrlhf-0.9.1.post1.data/purelib/openrlhf/cli/train_rm.py
openrlhf-0.9.1.post1.data/purelib/openrlhf/cli/train_sft.py
openrlhf-0.9.1.post1.data/purelib/openrlhf/datasets/__init__.py
openrlhf-0.9.1.post1.data/purelib/openrlhf/datasets/process_reward_dataset.py
openrlhf-0.9.1.post1.data/purelib/openrlhf/datasets/prompts_dataset.py
openrlhf-0.9.1.post1.data/purelib/openrlhf/datasets/reward_dataset.py
openrlhf-0.9.1.post1.data/purelib/openrlhf/datasets/sft_dataset.py
openrlhf-0.9.1.post1.data/purelib/openrlhf/datasets/unpaired_preference_dataset.py
openrlhf-0.9.1.post1.data/purelib/openrlhf/datasets/utils.py
openrlhf-0.9.1.post1.data/purelib/openrlhf/models/__init__.py
openrlhf-0.9.1.post1.data/purelib/openrlhf/models/actor.py
openrlhf-0.9.1.post1.data/purelib/openrlhf/models/loss.py
openrlhf-0.9.1.post1.data/purelib/openrlhf/models/model.py
openrlhf-0.9.1.post1.data/purelib/openrlhf/models/ring_attn_utils.py
openrlhf-0.9.1.post1.data/purelib/openrlhf/models/utils.py
openrlhf-0.9.1.post1.data/purelib/openrlhf/trainer/__init__.py
openrlhf-0.9.1.post1.data/purelib/openrlhf/trainer/dpo_trainer.py
openrlhf-0.9.1.post1.data/purelib/openrlhf/trainer/kd_trainer.py
openrlhf-0.9.1.post1.data/purelib/openrlhf/trainer/kto_trainer.py
openrlhf-0.9.1.post1.data/purelib/openrlhf/trainer/ppo_trainer.py
openrlhf-0.9.1.post1.dist-info/LICENSE
openrlhf-0.9.1.post1.dist-info/METADATA
openrlhf-0.9.1.post1.dist-info/WHEEL
openrlhf-0.9.1.post1.dist-info/top_level.txt
openrlhf-0.9.1.post1.dist-info/RECORD
