Metadata-Version: 2.1
Name: openrlhf
Version: 0.9.1.post1
Summary: A Ray-based High-performance RLHF framework.
Author: OpenRLHF Team
Classifier: Programming Language :: Python :: 3.10
Classifier: Programming Language :: Python :: 3.11
Classifier: Programming Language :: Python :: 3.12
Classifier: Environment :: GPU :: NVIDIA CUDA
Classifier: Topic :: Scientific/Engineering :: Artificial Intelligence
Classifier: Topic :: System :: Distributed Computing
Requires-Python: >=3.10
License-File: LICENSE
Requires-Dist: accelerate
Requires-Dist: aiohttp
Requires-Dist: bitsandbytes
Requires-Dist: datasets
Requires-Dist: deepspeed==0.18.3
Requires-Dist: einops
Requires-Dist: flash-attn==2.8.3
Requires-Dist: grpcio>=1.74.0
Requires-Dist: isort
Requires-Dist: jsonlines
Requires-Dist: loralib
Requires-Dist: optimum
Requires-Dist: optree>=0.13.0
Requires-Dist: packaging
Requires-Dist: peft
Requires-Dist: pynvml>=12.0.0
Requires-Dist: ray[default]==2.48.0
Requires-Dist: tensorboard
Requires-Dist: torch
Requires-Dist: torchdata
Requires-Dist: torchmetrics
Requires-Dist: tqdm
Requires-Dist: transformers==4.57.3
Requires-Dist: transformers-stream-generator
Requires-Dist: wandb
Requires-Dist: wheel
Provides-Extra: liger
Requires-Dist: liger-kernel; extra == "liger"
Provides-Extra: ring
Requires-Dist: ring-flash-attn; extra == "ring"
Provides-Extra: vllm
Requires-Dist: vllm==0.13.0; extra == "vllm"
Provides-Extra: vllm_latest
Requires-Dist: vllm>0.13.0; extra == "vllm-latest"
